SimLUCA_Blade/AnalyzeSys.py
SimLUCA_Blade/Animation.py
SimLUCA_Blade/ReactionLan/ChemSubs.py
SimLUCA_Blade/ReactionLan/Reaction.py
SimLUCA_Blade/ReactionLan/ReactionRateExpression.py
SimLUCA_Blade/ReactionLan/__init__.py
SimLUCA_Blade/ReactionSys.py
SimLUCA_Blade/SolveSys.py
SimLUCA_Blade/VolumeTessellation/Container.py
SimLUCA_Blade/VolumeTessellation/Diffusion.py
SimLUCA_Blade/VolumeTessellation/__init__.py
SimLUCA_Blade/__init__.py
simluca_blade-0.1.5.dist-info/METADATA
simluca_blade-0.1.5.dist-info/WHEEL
simluca_blade-0.1.5.dist-info/licenses/LICENSE
simluca_blade-0.1.5.dist-info/RECORD
